{
  "version": "tree-0.1",
  "tree": {
    "id": "App",
    "path": "",
    "children": {
      "Tree": {
        "id": "Tree",
        "path": "Tree",
        "constructInfo": {
          "fqn": "constructs.Construct",
          "version": "10.0.94"
        }
      },
      "AwsCdkStack": {
        "id": "AwsCdkStack",
        "path": "AwsCdkStack",
        "children": {
          "Application": {
            "id": "Application",
            "path": "AwsCdkStack/Application",
            "attributes": {
              "aws:cdk:cloudformation:type": "AWS::ElasticBeanstalk::Application",
              "aws:cdk:cloudformation:props": {
                "applicationName": "NexScore"
              }
            },
            "constructInfo": {
              "fqn": "aws-cdk-lib.aws_elasticbeanstalk.CfnApplication",
              "version": "2.17.0"
            }
          },
          "CustomEBRole": {
            "id": "CustomEBRole",
            "path": "AwsCdkStack/CustomEBRole",
            "children": {
              "Resource": {
                "id": "Resource",
                "path": "AwsCdkStack/CustomEBRole/Resource",
                "attributes": {
                  "aws:cdk:cloudformation:type": "AWS::IAM::Role",
                  "aws:cdk:cloudformation:props": {
                    "assumeRolePolicyDocument": {
                      "Statement": [
                        {
                          "Action": "sts:AssumeRole",
                          "Effect": "Allow",
                          "Principal": {
                            "Service": {
                              "Fn::Join": [
                                "",
                                [
                                  "ec2.",
                                  {
                                    "Ref": "AWS::URLSuffix"
                                  }
                                ]
                              ]
                            }
                          }
                        }
                      ],
                      "Version": "2012-10-17"
                    }
                  }
                },
                "constructInfo": {
                  "fqn": "aws-cdk-lib.aws_iam.CfnRole",
                  "version": "2.17.0"
                }
              }
            },
            "constructInfo": {
              "fqn": "aws-cdk-lib.aws_iam.Role",
              "version": "2.17.0"
            }
          },
          "CustomInstanceProfile": {
            "id": "CustomInstanceProfile",
            "path": "AwsCdkStack/CustomInstanceProfile",
            "attributes": {
              "aws:cdk:cloudformation:type": "AWS::IAM::InstanceProfile",
              "aws:cdk:cloudformation:props": {
                "roles": [
                  {
                    "Ref": "CustomEBRoleCA0874C6"
                  }
                ]
              }
            },
            "constructInfo": {
              "fqn": "aws-cdk-lib.aws_iam.CfnInstanceProfile",
              "version": "2.17.0"
            }
          },
          "Environment": {
            "id": "Environment",
            "path": "AwsCdkStack/Environment",
            "attributes": {
              "aws:cdk:cloudformation:type": "AWS::ElasticBeanstalk::Environment",
              "aws:cdk:cloudformation:props": {
                "applicationName": "NexScore",
                "environmentName": "NexScore-env",
                "optionSettings": [
                  {
                    "namespace": "aws:autoscaling:launchconfiguration",
                    "optionName": "IamInstanceProfile",
                    "value": {
                      "Fn::GetAtt": [
                        "CustomInstanceProfile",
                        "Arn"
                      ]
                    }
                  },
                  {
                    "namespace": "aws:autoscaling:launchconfiguration",
                    "optionName": "InstanceType",
                    "value": "t3.small"
                  },
                  {
                    "namespace": "aws:elasticbeanstalk:application:environment",
                    "optionName": "SERVER_PORT",
                    "value": "5000"
                  }
                ],
                "solutionStackName": "64bit Amazon Linux 2 v3.2.12 running Corretto 11"
              }
            },
            "constructInfo": {
              "fqn": "aws-cdk-lib.aws_elasticbeanstalk.CfnEnvironment",
              "version": "2.17.0"
            }
          },
          "Player": {
            "id": "Player",
            "path": "AwsCdkStack/Player",
            "children": {
              "Resource": {
                "id": "Resource",
                "path": "AwsCdkStack/Player/Resource",
                "attributes": {
                  "aws:cdk:cloudformation:type": "AWS::DynamoDB::Table",
                  "aws:cdk:cloudformation:props": {
                    "keySchema": [
                      {
                        "attributeName": "puuid",
                        "keyType": "HASH"
                      }
                    ],
                    "attributeDefinitions": [
                      {
                        "attributeName": "puuid",
                        "attributeType": "S"
                      }
                    ],
                    "provisionedThroughput": {
                      "readCapacityUnits": 5,
                      "writeCapacityUnits": 5
                    }
                  }
                },
                "constructInfo": {
                  "fqn": "aws-cdk-lib.aws_dynamodb.CfnTable",
                  "version": "2.17.0"
                }
              },
              "ScalingRole": {
                "id": "ScalingRole",
                "path": "AwsCdkStack/Player/ScalingRole",
                "constructInfo": {
                  "fqn": "aws-cdk-lib.Resource",
                  "version": "2.17.0"
                }
              }
            },
            "constructInfo": {
              "fqn": "aws-cdk-lib.aws_dynamodb.Table",
              "version": "2.17.0"
            }
          },
          "Match": {
            "id": "Match",
            "path": "AwsCdkStack/Match",
            "children": {
              "Resource": {
                "id": "Resource",
                "path": "AwsCdkStack/Match/Resource",
                "attributes": {
                  "aws:cdk:cloudformation:type": "AWS::DynamoDB::Table",
                  "aws:cdk:cloudformation:props": {
                    "keySchema": [
                      {
                        "attributeName": "matchid",
                        "keyType": "HASH"
                      }
                    ],
                    "attributeDefinitions": [
                      {
                        "attributeName": "matchid",
                        "attributeType": "S"
                      }
                    ],
                    "provisionedThroughput": {
                      "readCapacityUnits": 5,
                      "writeCapacityUnits": 5
                    }
                  }
                },
                "constructInfo": {
                  "fqn": "aws-cdk-lib.aws_dynamodb.CfnTable",
                  "version": "2.17.0"
                }
              },
              "ScalingRole": {
                "id": "ScalingRole",
                "path": "AwsCdkStack/Match/ScalingRole",
                "constructInfo": {
                  "fqn": "aws-cdk-lib.Resource",
                  "version": "2.17.0"
                }
              }
            },
            "constructInfo": {
              "fqn": "aws-cdk-lib.aws_dynamodb.Table",
              "version": "2.17.0"
            }
          },
          "CDKMetadata": {
            "id": "CDKMetadata",
            "path": "AwsCdkStack/CDKMetadata",
            "children": {
              "Default": {
                "id": "Default",
                "path": "AwsCdkStack/CDKMetadata/Default",
                "constructInfo": {
                  "fqn": "aws-cdk-lib.CfnResource",
                  "version": "2.17.0"
                }
              },
              "Condition": {
                "id": "Condition",
                "path": "AwsCdkStack/CDKMetadata/Condition",
                "constructInfo": {
                  "fqn": "aws-cdk-lib.CfnCondition",
                  "version": "2.17.0"
                }
              }
            },
            "constructInfo": {
              "fqn": "constructs.Construct",
              "version": "10.0.94"
            }
          }
        },
        "constructInfo": {
          "fqn": "aws-cdk-lib.Stack",
          "version": "2.17.0"
        }
      }
    },
    "constructInfo": {
      "fqn": "aws-cdk-lib.App",
      "version": "2.17.0"
    }
  }
}